aibase/__init__.py
aibase/common/__init__.py
aibase/common/base_svc.py
aibase/common/comm_define.py
aibase/common/logger.py
aibase/common/project_path.py
aibase/middleware/__init__.py
aibase/middleware/kafka_util.py
aibase/middleware/redis_util.py
aibase/utils/__init__.py
aibase/utils/image.py
aibase/utils/time.py
aibase-0.0.3.dist-info/METADATA
aibase-0.0.3.dist-info/WHEEL
aibase-0.0.3.dist-info/top_level.txt
aibase-0.0.3.dist-info/RECORD
