Metadata-Version: 2.1
Name: aibase
Version: 0.0.3
Summary: 基础包
Home-page: http://svn.51iwifi.com/repos/AI/bi/code/trunk/aibase
Author: gmo_ye
Author-email: gmo_ye@163.com
License: UNKNOWN
Platform: UNKNOWN
Classifier: Programming Language :: Python :: 3
Classifier: License :: OSI Approved :: MIT License
Classifier: Operating System :: OS Independent
Requires-Python: >=3.6
Requires-Dist: Pillow (>=6.1.0)
Requires-Dist: flask (>=1.1.1)
Requires-Dist: redis (>=3.3.11)
Requires-Dist: kafka (>=1.3.5)
